alu.sv
/*
* Primitive alu example for Verilator example
*
 * File name: alu.sv
 * Author: Norbertas Kremeris 2021
 *
	 */
	typedef enum logic [1:0] {
		add     = 2'h1,
		sub     = 2'h2,
		nop     = 2'h0
	} operation_t /*verilator public*/;

	module alu #(
		parameter WIDTH = 6
	) (
		input clk,
		input rst,

		input  operation_t  op_in,
		input  [WIDTH-1:0]  a_in,
		input  [WIDTH-1:0]  b_in,
		input               in_valid,

		output logic [WIDTH-1:0]  out,
		output logic              out_valid
	);

	operation_t  op_in_r;
	logic  [WIDTH-1:0]  a_in_r;
	logic  [WIDTH-1:0]  b_in_r;
	logic               in_valid_r;
	logic  [WIDTH-1:0]  result;

	// Register all inputs
	always_ff @ (posedge clk, posedge rst) begin
		if (rst) begin
			op_in_r     <= nop;
			a_in_r      <= '0;
			b_in_r      <= '0;
			in_valid_r  <= '0;
		end else begin
			op_in_r    <= op_in;
			a_in_r     <= a_in;
			b_in_r     <= b_in;
			in_valid_r <= in_valid;
		end
	end

	// Compute the result
	always_comb begin
		result = '0;
		if (in_valid_r) begin
			case (op_in_r)
				add: result = a_in_r + b_in_r;
				sub: result = a_in_r + (~b_in_r+1'b1);
				default: result = '0;
			endcase
		end
	end

	// Register outputs
	always_ff @ (posedge clk, posedge rst) begin
		if (rst) begin
			out       <= '0;
			out_valid <= '0;
		end else begin
			out       <= result;
			out_valid <= in_valid_r;
		end
	end

	endmodule;

waveform.vcd
$version Generated by VerilatedVcd $end
$timescale 1ps $end

 $scope module TOP $end
  $var wire  6 + a_in [5:0] $end
  $var wire  6 , b_in [5:0] $end
  $var wire  1 ( clk $end
  $var wire  1 - in_valid $end
  $var wire  2 * op_in [1:0] $end
  $var wire  6 . out [5:0] $end
  $var wire  1 / out_valid $end
  $var wire  1 ) rst $end
  $scope module alu $end
   $var wire 32 0 WIDTH [31:0] $end
   $var wire  6 + a_in [5:0] $end
   $var wire  6 $ a_in_r [5:0] $end
   $var wire  6 , b_in [5:0] $end
   $var wire  6 % b_in_r [5:0] $end
   $var wire  1 ( clk $end
   $var wire  1 - in_valid $end
   $var wire  1 & in_valid_r $end
   $var wire  2 * op_in [1:0] $end
   $var wire  2 # op_in_r [1:0] $end
   $var wire  6 . out [5:0] $end
   $var wire  1 / out_valid $end
   $var wire  6 ' result [5:0] $end
   $var wire  1 ) rst $end
  $upscope $end
 $upscope $end
$enddefinitions $end


#0
b11 #
b010011 $
b100001 %
1&
b000000 '
1(
0)
b10 *
b100100 +
b111000 ,
0-
b110110 .
0/
b00000000000000000000000000000110 0
#1
0(
#2
b10 #
b100100 $
b111000 %
0&
1(
b000000 .
1/
#3
b00 #
b000000 $
b000000 %
0(
1)
b00 *
b000000 +
b000000 ,
0/
#4
1(
#5
0(
#6
1(
0)
#7
0(
#8
1(
#9
0(
#10
1(
#11
0(
#12
1(
#13
0(
#14
1(
#15
0(
#16
1(
#17
0(
#18
1(
b01 *
b000101 +
b000011 ,
1-
#19
0(
#20
b01 #
b000101 $
b000011 %
1&
b001000 '
1(
0-
#21
0(
#22
0&
b000000 '
1(
b001000 .
1/
#23
0(
#24
1(
b000000 .
0/
#25
0(
#26
1(
#27
0(
#28
1(
#29
0(
#30
1(
#31
0(
#32
1(
#33
0(
#34
1(
#35
0(
#36
1(
#37
0(
#38
1(
b10 *
1-
#39
0(
#40
b10 #
1&
b000010 '
1(
0-
#41
0(
#42
0&
b000000 '
1(
b000010 .
1/
#43
0(
#44
1(
b000000 .
0/
