alu.sv
/*
* Primitive alu example for Verilator example
*
 * File name: alu.sv
 * Author: Norbertas Kremeris 2021
 *
	 */
	typedef enum logic [1:0] {
		add     = 2'h1,
		sub     = 2'h2,
		nop     = 2'h0
	} operation_t /*verilator public*/;

	module alu #(
		parameter WIDTH = 6
	) (
		input clk,
		input rst,

		input  operation_t  op_in,
		input  [WIDTH-1:0]  a_in,
		input  [WIDTH-1:0]  b_in,
		input               in_valid,

		output logic [WIDTH-1:0]  out,
		output logic              out_valid
	);

	operation_t  op_in_r;
	logic  [WIDTH-1:0]  a_in_r;
	logic  [WIDTH-1:0]  b_in_r;
	logic               in_valid_r;
	logic  [WIDTH-1:0]  result;

	// Register all inputs: always_ff keyword is used to define a synchronous procedural block.
	always_ff @ (posedge clk, posedge rst) begin
		if (rst) begin
			op_in_r     <= nop;
			a_in_r      <= '0;
			b_in_r      <= '0;
			in_valid_r  <= '0;
		end else begin
			op_in_r    <= op_in;
			a_in_r     <= a_in;
			b_in_r     <= b_in;
			in_valid_r <= in_valid;
		end
	end

	// Compute the result: always_comb keyword is used to define a combinational procedural block.
	always_comb begin
		result = '0;
		if (in_valid_r) begin
			case (op_in_r)
				add: result = a_in_r + b_in_r;
				sub: result = a_in_r + (~b_in_r+1'b1);
				default: result = '0;
			endcase
		end
	end

	// Register outputs
	always_ff @ (posedge clk, posedge rst) begin
		if (rst) begin
			out       <= '0;
			out_valid <= '0;
		end else begin
			out       <= result;
			out_valid <= in_valid_r;
		end
	end

	endmodule;

waveform.vcd
$version Generated by VerilatedVcd $end
$timescale 1ps $end

 $scope module TOP $end
  $var wire  6 + a_in [5:0] $end
  $var wire  6 , b_in [5:0] $end
  $var wire  1 ( clk $end
  $var wire  1 - in_valid $end
  $var wire  2 * op_in [1:0] $end
  $var wire  6 . out [5:0] $end
  $var wire  1 / out_valid $end
  $var wire  1 ) rst $end
  $scope module alu $end
   $var wire 32 0 WIDTH [31:0] $end
   $var wire  6 + a_in [5:0] $end
   $var wire  6 $ a_in_r [5:0] $end
   $var wire  6 , b_in [5:0] $end
   $var wire  6 % b_in_r [5:0] $end
   $var wire  1 ( clk $end
   $var wire  1 - in_valid $end
   $var wire  1 & in_valid_r $end
   $var wire  2 * op_in [1:0] $end
   $var wire  2 # op_in_r [1:0] $end
   $var wire  6 . out [5:0] $end
   $var wire  1 / out_valid $end
   $var wire  6 ' result [5:0] $end
   $var wire  1 ) rst $end
  $upscope $end
 $upscope $end
$enddefinitions $end


#0
b11 #
b010011 $
b100001 %
1&
b000000 '
1(
0)
b10 *
b100100 +
b111000 ,
0-
b110110 .
0/
b00000000000000000000000000000110 0
#1
0(
#2
b10 #
b100100 $
b111000 %
0&
1(
b000000 .
1/
#3
b00 #
b000000 $
b000000 %
0(
1)
b00 *
b000000 +
b000000 ,
0/
#4
1(
#5
0(
#6
1(
0)
#7
0(
#8
1(
#9
0(
#10
1(
b01 *
b010010 +
b000011 ,
1-
#11
0(
#12
b01 #
b010010 $
b000011 %
1&
b010101 '
1(
b10 *
b000100 ,
#13
0(
#14
b10 #
b000100 %
b001110 '
1(
0-
b010101 .
1/
#15
0(
#16
0&
b000000 '
1(
b01 *
b010000 +
b000000 ,
1-
b001110 .
#17
0(
#18
b01 #
b010000 $
b000000 %
1&
b010000 '
1(
b10 *
b001010 +
b000101 ,
b000000 .
0/
#19
0(
#20
b10 #
b001010 $
b000101 %
b000101 '
1(
0-
b010000 .
1/
#21
0(
#22
0&
b000000 '
1(
b01 *
b010010 +
b000011 ,
1-
b000101 .
#23
0(
#24
b01 #
b010010 $
b000011 %
1&
b010101 '
1(
b10 *
b001111 +
b000111 ,
b000000 .
0/
#25
0(
#26
b10 #
b001111 $
b000111 %
b001000 '
1(
0-
b010101 .
1/
#27
0(
#28
0&
b000000 '
1(
b01 *
b010000 +
b000011 ,
1-
b001000 .
#29
0(
#30
b01 #
b010000 $
b000011 %
1&
b010011 '
1(
b10 *
b001110 +
b000100 ,
b000000 .
0/
#31
0(
#32
b10 #
b001110 $
b000100 %
b001010 '
1(
0-
b010011 .
1/
#33
0(
#34
0&
b000000 '
1(
b01 *
b000101 ,
1-
b001010 .
#35
0(
#36
b01 #
b000101 %
1&
b010011 '
1(
b10 *
b010001 +
b000011 ,
b000000 .
0/
#37
0(
#38
b10 #
b010001 $
b000011 %
b001110 '
1(
0-
b010011 .
1/
#39
0(
#40
0&
b000000 '
1(
b01 *
b000111 ,
1-
b001110 .
#41
0(
#42
b01 #
b000111 %
1&
b011000 '
1(
b10 *
b010100 +
b000000 ,
b000000 .
0/
#43
0(
#44
b10 #
b010100 $
b000000 %
b010100 '
1(
0-
b011000 .
1/
#45
0(
#46
0&
b000000 '
1(
b01 *
b010000 +
b000010 ,
1-
b010100 .
#47
0(
#48
b01 #
b010000 $
b000010 %
1&
b010010 '
1(
b10 *
b001111 +
b000110 ,
b000000 .
0/
#49
0(
#50
b10 #
b001111 $
b000110 %
b001001 '
1(
0-
b010010 .
1/
#51
0(
#52
0&
b000000 '
1(
b01 *
b001011 +
b000101 ,
1-
b001001 .
#53
0(
#54
b01 #
b001011 $
b000101 %
1&
b010000 '
1(
b10 *
b010010 +
b000100 ,
b000000 .
0/
#55
0(
#56
b10 #
b010010 $
b000100 %
b001110 '
1(
0-
b010000 .
1/
#57
0(
#58
0&
b000000 '
1(
b01 *
b010001 +
b001000 ,
1-
b001110 .
#59
0(
#60
b01 #
b010001 $
b001000 %
1&
b011001 '
1(
b10 *
b010010 +
b000000 ,
b000000 .
0/
#61
0(
#62
b10 #
b010010 $
b000000 %
b010010 '
1(
0-
b011001 .
1/
#63
0(
#64
0&
b000000 '
1(
b01 *
b010000 +
b000010 ,
1-
b010010 .
#65
0(
#66
b01 #
b010000 $
b000010 %
1&
b010010 '
1(
b10 *
b001010 +
b000001 ,
b000000 .
0/
#67
0(
#68
b10 #
b001010 $
b000001 %
b001001 '
1(
0-
b010010 .
1/
#69
0(
#70
0&
b000000 '
1(
b01 *
b000101 ,
1-
b001001 .
#71
0(
#72
b01 #
b000101 %
1&
b001111 '
1(
b10 *
b010010 +
b000001 ,
b000000 .
0/
#73
0(
#74
b10 #
b010010 $
b000001 %
b010001 '
1(
0-
b001111 .
1/
#75
0(
#76
0&
b000000 '
1(
b01 *
b001010 +
b001000 ,
1-
b010001 .
#77
0(
#78
b01 #
b001010 $
b001000 %
1&
b010010 '
1(
b10 *
b001111 +
b000111 ,
b000000 .
0/
#79
0(
#80
b10 #
b001111 $
b000111 %
b001000 '
1(
0-
b010010 .
1/
#81
0(
#82
0&
b000000 '
1(
b01 *
b010001 +
b000011 ,
1-
b001000 .
#83
0(
#84
b01 #
b010001 $
b000011 %
1&
b010100 '
1(
b10 *
b001010 +
b000000 ,
b000000 .
0/
#85
0(
#86
b10 #
b001010 $
b000000 %
b001010 '
1(
0-
b010100 .
1/
#87
0(
#88
0&
b000000 '
1(
b01 *
b001101 +
b000101 ,
1-
b001010 .
#89
0(
#90
b01 #
b001101 $
b000101 %
1&
b010010 '
1(
b10 *
b010001 +
b000001 ,
b000000 .
0/
#91
0(
#92
b10 #
b010001 $
b000001 %
b010000 '
1(
0-
b010010 .
1/
#93
0(
#94
0&
b000000 '
1(
b01 *
b001010 +
b000110 ,
1-
b010000 .
#95
0(
#96
b01 #
b001010 $
b000110 %
1&
b010000 '
1(
b10 *
b001111 +
b000011 ,
b000000 .
0/
#97
0(
#98
b10 #
b001111 $
b000011 %
b001100 '
1(
0-
b010000 .
1/
#99
0(
#100
0&
b000000 '
1(
b01 *
b000001 ,
1-
b001100 .
#101
0(
#102
b01 #
b000001 %
1&
b010000 '
1(
b10 *
b010100 +
b000110 ,
b000000 .
0/
#103
0(
#104
b10 #
b010100 $
b000110 %
b001110 '
1(
0-
b010000 .
1/
#105
0(
#106
0&
b000000 '
1(
b01 *
b000101 ,
1-
b001110 .
#107
0(
#108
b01 #
b000101 %
1&
b011001 '
1(
b10 *
b010011 +
b000000 ,
b000000 .
0/
#109
0(
#110
b10 #
b010011 $
b000000 %
b010011 '
1(
0-
b011001 .
1/
#111
0(
#112
0&
b000000 '
1(
b01 *
b010001 +
b000111 ,
1-
b010011 .
#113
0(
#114
b01 #
b010001 $
b000111 %
1&
b011000 '
1(
b10 *
b001000 ,
b000000 .
0/
#115
0(
#116
b10 #
b001000 %
b001001 '
1(
0-
b011000 .
1/
#117
0(
#118
0&
b000000 '
1(
b01 *
b010000 +
b000101 ,
1-
b001001 .
#119
0(
#120
b01 #
b010000 $
b000101 %
1&
b010101 '
1(
b10 *
b010011 +
b001000 ,
b000000 .
0/
#121
0(
#122
b10 #
b010011 $
b001000 %
b001011 '
1(
0-
b010101 .
1/
#123
0(
#124
0&
b000000 '
1(
b01 *
b001111 +
b000010 ,
1-
b001011 .
#125
0(
#126
b01 #
b001111 $
b000010 %
1&
b010001 '
1(
b10 *
b010010 +
b000000 ,
b000000 .
0/
#127
0(
#128
b10 #
b010010 $
b000000 %
b010010 '
1(
0-
b010001 .
1/
#129
0(
#130
0&
b000000 '
1(
b01 *
b010011 +
b000110 ,
1-
b010010 .
#131
0(
#132
b01 #
b010011 $
b000110 %
1&
b011001 '
1(
b10 *
b001011 +
b000000 ,
b000000 .
0/
#133
0(
#134
b10 #
b001011 $
b000000 %
b001011 '
1(
0-
b011001 .
1/
#135
0(
#136
0&
b000000 '
1(
b01 *
b010100 +
b000100 ,
1-
b001011 .
#137
0(
#138
b01 #
b010100 $
b000100 %
1&
b011000 '
1(
b10 *
b010000 +
b000111 ,
b000000 .
0/
#139
0(
#140
b10 #
b010000 $
b000111 %
b001001 '
1(
0-
b011000 .
1/
#141
0(
#142
0&
b000000 '
1(
b01 *
b001110 +
b000101 ,
1-
b001001 .
#143
0(
#144
b01 #
b001110 $
b000101 %
1&
b010011 '
1(
b10 *
b010100 +
b000110 ,
b000000 .
0/
#145
0(
#146
b10 #
b010100 $
b000110 %
b001110 '
1(
0-
b010011 .
1/
#147
0(
#148
0&
b000000 '
1(
b01 *
b001010 +
b000101 ,
1-
b001110 .
#149
0(
#150
b01 #
b001010 $
b000101 %
1&
b001111 '
1(
b10 *
b010011 +
b000000 .
0/
#151
0(
#152
b10 #
b010011 $
b001110 '
1(
0-
b001111 .
1/
#153
0(
#154
0&
b000000 '
1(
b01 *
b001101 +
b001000 ,
1-
b001110 .
#155
0(
#156
b01 #
b001101 $
b001000 %
1&
b010101 '
1(
b10 *
b001111 +
b000011 ,
b000000 .
0/
#157
0(
#158
b10 #
b001111 $
b000011 %
b001100 '
1(
0-
b010101 .
1/
#159
0(
#160
0&
b000000 '
1(
b01 *
b010010 +
b001000 ,
1-
b001100 .
#161
0(
#162
b01 #
b010010 $
b001000 %
1&
b011010 '
1(
b10 *
b010100 +
b000000 .
0/
#163
0(
#164
b10 #
b010100 $
b001100 '
1(
0-
b011010 .
1/
#165
0(
#166
0&
b000000 '
1(
b01 *
b001111 +
1-
b001100 .
#167
0(
#168
b01 #
b001111 $
1&
b010111 '
1(
b10 *
b010000 +
b000101 ,
b000000 .
0/
#169
0(
#170
b10 #
b010000 $
b000101 %
b001011 '
1(
0-
b010111 .
1/
#171
0(
#172
0&
b000000 '
1(
b01 *
b001111 +
b000110 ,
1-
b001011 .
#173
0(
#174
b01 #
b001111 $
b000110 %
1&
b010101 '
1(
b10 *
b010011 +
b000000 .
0/
#175
0(
#176
b10 #
b010011 $
b001101 '
1(
0-
b010101 .
1/
#177
0(
#178
0&
b000000 '
1(
b01 *
b001010 +
1-
b001101 .
#179
0(
#180
b01 #
b001010 $
1&
b010000 '
1(
b10 *
b001101 +
b000010 ,
b000000 .
0/
#181
0(
#182
b10 #
b001101 $
b000010 %
b001011 '
1(
0-
b010000 .
1/
#183
0(
#184
0&
b000000 '
1(
b01 *
b001011 +
b000110 ,
1-
b001011 .
#185
0(
#186
b01 #
b001011 $
b000110 %
1&
b010001 '
1(
b10 *
b010010 +
b000101 ,
b000000 .
0/
#187
0(
#188
b10 #
b010010 $
b000101 %
b001101 '
1(
0-
b010001 .
1/
#189
0(
#190
0&
b000000 '
1(
b01 *
b001110 +
b000100 ,
1-
b001101 .
#191
0(
#192
b01 #
b001110 $
b000100 %
1&
b010010 '
1(
b10 *
b010010 +
b000110 ,
b000000 .
0/
#193
0(
#194
b10 #
b010010 $
b000110 %
b001100 '
1(
0-
b010010 .
1/
#195
0(
#196
0&
b000000 '
1(
b01 *
b010100 +
b001000 ,
1-
b001100 .
#197
0(
#198
b01 #
b010100 $
b001000 %
1&
b011100 '
1(
b10 *
b010011 +
b000100 ,
b000000 .
0/
#199
0(
#200
b10 #
b010011 $
b000100 %
b001111 '
1(
0-
b011100 .
1/
#201
0(
#202
0&
b000000 '
1(
b01 *
b010000 +
b000001 ,
1-
b001111 .
#203
0(
#204
b01 #
b010000 $
b000001 %
1&
b010001 '
1(
b10 *
b001010 +
b000000 ,
b000000 .
0/
#205
0(
#206
b10 #
b001010 $
b000000 %
b001010 '
1(
0-
b010001 .
1/
#207
0(
#208
0&
b000000 '
1(
b01 *
b001011 +
1-
b001010 .
#209
0(
#210
b01 #
b001011 $
1&
b001011 '
1(
b10 *
b001100 +
b000010 ,
b000000 .
0/
#211
0(
#212
b10 #
b001100 $
b000010 %
b001010 '
1(
0-
b001011 .
1/
#213
0(
#214
0&
b000000 '
1(
b01 *
b001011 +
b000111 ,
1-
b001010 .
#215
0(
#216
b01 #
b001011 $
b000111 %
1&
b010010 '
1(
b10 *
b000000 ,
b000000 .
0/
#217
0(
#218
b10 #
b000000 %
b001011 '
1(
0-
b010010 .
1/
#219
0(
#220
0&
b000000 '
1(
b01 *
b010011 +
b000111 ,
1-
b001011 .
#221
0(
#222
b01 #
b010011 $
b000111 %
1&
b011010 '
1(
b10 *
b010010 +
b000000 ,
b000000 .
0/
#223
0(
#224
b10 #
b010010 $
b000000 %
b010010 '
1(
0-
b011010 .
1/
#225
0(
#226
0&
b000000 '
1(
b01 *
b001110 +
b000001 ,
1-
b010010 .
#227
0(
#228
b01 #
b001110 $
b000001 %
1&
b001111 '
1(
b10 *
b010100 +
b000100 ,
b000000 .
0/
#229
0(
#230
b10 #
b010100 $
b000100 %
b010000 '
1(
0-
b001111 .
1/
#231
0(
#232
0&
b000000 '
1(
b01 *
b001111 +
b001000 ,
1-
b010000 .
#233
0(
#234
b01 #
b001111 $
b001000 %
1&
b010111 '
1(
b10 *
b010011 +
b000010 ,
b000000 .
0/
#235
0(
#236
b10 #
b010011 $
b000010 %
b010001 '
1(
0-
b010111 .
1/
#237
0(
#238
0&
b000000 '
1(
b01 *
b010100 +
b000101 ,
1-
b010001 .
#239
0(
#240
b01 #
b010100 $
b000101 %
1&
b011001 '
1(
b10 *
b001111 +
b000100 ,
b000000 .
0/
#241
0(
#242
b10 #
b001111 $
b000100 %
b001011 '
1(
0-
b011001 .
1/
#243
0(
#244
0&
b000000 '
1(
b01 *
b001110 +
b000011 ,
1-
b001011 .
#245
0(
#246
b01 #
b001110 $
b000011 %
1&
b010001 '
1(
b10 *
b001011 +
b000110 ,
b000000 .
0/
#247
0(
#248
b10 #
b001011 $
b000110 %
b000101 '
1(
0-
b010001 .
1/
#249
0(
#250
0&
b000000 '
1(
b01 *
b010011 +
b001000 ,
1-
b000101 .
#251
0(
#252
b01 #
b010011 $
b001000 %
1&
b011011 '
1(
b10 *
b001100 +
b000110 ,
b000000 .
0/
#253
0(
#254
b10 #
b001100 $
b000110 %
b000110 '
1(
0-
b011011 .
1/
#255
0(
#256
0&
b000000 '
1(
b01 *
b001010 +
b000101 ,
1-
b000110 .
#257
0(
#258
b01 #
b001010 $
b000101 %
1&
b001111 '
1(
b10 *
b010000 +
b000001 ,
b000000 .
0/
#259
0(
#260
b10 #
b010000 $
b000001 %
1(
0-
b001111 .
1/
#261
0(
#262
0&
b000000 '
1(
b01 *
b001011 +
b000101 ,
1-
#263
0(
#264
b01 #
b001011 $
b000101 %
1&
b010000 '
1(
b10 *
b001010 +
b001000 ,
b000000 .
0/
#265
0(
#266
b10 #
b001010 $
b001000 %
b000010 '
1(
0-
b010000 .
1/
#267
0(
#268
0&
b000000 '
1(
b01 *
b001111 +
b000101 ,
1-
b000010 .
#269
0(
#270
b01 #
b001111 $
b000101 %
1&
b010100 '
1(
b10 *
b001110 +
b000000 ,
b000000 .
0/
#271
0(
#272
b10 #
b001110 $
b000000 %
b001110 '
1(
0-
b010100 .
1/
#273
0(
#274
0&
b000000 '
1(
b01 *
b000101 ,
1-
b001110 .
#275
0(
#276
b01 #
b000101 %
1&
b010011 '
1(
b10 *
b000111 ,
b000000 .
0/
#277
0(
#278
b10 #
b000111 %
b000111 '
1(
0-
b010011 .
1/
#279
0(
#280
0&
b000000 '
1(
b01 *
b001101 +
b000100 ,
1-
b000111 .
#281
0(
#282
b01 #
b001101 $
b000100 %
1&
b010001 '
1(
b10 *
b001010 +
b000001 ,
b000000 .
0/
#283
0(
#284
b10 #
b001010 $
b000001 %
b001001 '
1(
0-
b010001 .
1/
#285
0(
#286
0&
b000000 '
1(
b01 *
b010000 +
b000110 ,
1-
b001001 .
#287
0(
#288
b01 #
b010000 $
b000110 %
1&
b010110 '
1(
b10 *
b001010 +
b001000 ,
b000000 .
0/
#289
0(
#290
b10 #
b001010 $
b001000 %
b000010 '
1(
0-
b010110 .
1/
#291
0(
#292
0&
b000000 '
1(
b01 *
b000010 ,
1-
b000010 .
#293
0(
#294
b01 #
b000010 %
1&
b001100 '
1(
b10 *
b010000 +
b000000 ,
b000000 .
0/
#295
0(
#296
b10 #
b010000 $
b000000 %
b010000 '
1(
0-
b001100 .
1/
#297
0(
#298
0&
b000000 '
1(
b01 *
b010011 +
b000011 ,
1-
b010000 .
