alu.sv
/*
* Primitive alu example for Verilator example
*
 * File name: alu.sv
 * Author: Norbertas Kremeris 2021
 *
	 */
	typedef enum logic [1:0] {
		add     = 2'h1,
		sub     = 2'h2,
		nop     = 2'h0
	} operation_t /*verilator public*/;

	module alu #(
		parameter WIDTH = 6
	) (
		input clk,
		input rst,

		input  operation_t  op_in,
		input  [WIDTH-1:0]  a_in,
		input  [WIDTH-1:0]  b_in,
		input               in_valid,

		output logic [WIDTH-1:0]  out,
		output logic              out_valid
	);

	operation_t  op_in_r;
	logic  [WIDTH-1:0]  a_in_r;
	logic  [WIDTH-1:0]  b_in_r;
	logic               in_valid_r;
	logic  [WIDTH-1:0]  result;

	// Register all inputs
	always_ff @ (posedge clk, posedge rst) begin
		if (rst) begin
			op_in_r     <= nop;
			a_in_r      <= '0;
			b_in_r      <= '0;
			in_valid_r  <= '0;
		end else begin
			op_in_r    <= op_in;
			a_in_r     <= a_in;
			b_in_r     <= b_in;
			in_valid_r <= in_valid;
		end
	end

	// Compute the result
	always_comb begin
		result = '0;
		if (in_valid_r) begin
			case (op_in_r)
				add: result = a_in_r + b_in_r;
				sub: result = a_in_r + (~b_in_r+1'b1);
				default: result = '0;
			endcase
		end
	end

	// Register outputs
	always_ff @ (posedge clk, posedge rst) begin
		if (rst) begin
			out       <= '0;
			out_valid <= '0;
		end else begin
			out       <= result;
			out_valid <= in_valid_r;
		end
	end

	endmodule;

waveform.vcd
$version Generated by VerilatedVcd $end
$timescale 1ps $end

 $scope module TOP $end
  $var wire  6 + a_in [5:0] $end
  $var wire  6 , b_in [5:0] $end
  $var wire  1 ( clk $end
  $var wire  1 - in_valid $end
  $var wire  2 * op_in [1:0] $end
  $var wire  6 . out [5:0] $end
  $var wire  1 / out_valid $end
  $var wire  1 ) rst $end
  $scope module alu $end
   $var wire 32 0 WIDTH [31:0] $end
   $var wire  6 + a_in [5:0] $end
   $var wire  6 $ a_in_r [5:0] $end
   $var wire  6 , b_in [5:0] $end
   $var wire  6 % b_in_r [5:0] $end
   $var wire  1 ( clk $end
   $var wire  1 - in_valid $end
   $var wire  1 & in_valid_r $end
   $var wire  2 * op_in [1:0] $end
   $var wire  2 # op_in_r [1:0] $end
   $var wire  6 . out [5:0] $end
   $var wire  1 / out_valid $end
   $var wire  6 ' result [5:0] $end
   $var wire  1 ) rst $end
  $upscope $end
 $upscope $end
$enddefinitions $end


#0
b11 #
b010011 $
b100001 %
1&
b000000 '
1(
0)
b10 *
b100100 +
b111000 ,
0-
b110110 .
0/
b00000000000000000000000000000110 0
#1
0(
#2
b10 #
b100100 $
b111000 %
0&
1(
b000000 .
1/
#3
b00 #
b000000 $
b000000 %
0(
1)
b00 *
b000000 +
b000000 ,
0/
#4
1(
#5
0(
#6
1(
0)
#7
0(
#8
1(
1-
#9
0(
#10
1&
1(
#11
0(
#12
1(
1/
#13
0(
#14
1(
#15
0(
#16
1(
#17
0(
#18
1(
0-
#19
0(
#20
0&
1(
#21
0(
#22
1(
0/
#23
0(
#24
1(
#25
0(
#26
1(
#27
0(
#28
1(
#29
0(
#30
1(
#31
0(
#32
1(
1-
#33
0(
#34
1&
1(
#35
0(
#36
1(
0-
1/
#37
0(
#38
0&
1(
#39
0(
#40
1(
0/
#41
0(
#42
1(
1-
#43
0(
#44
1&
1(
0-
#45
0(
#46
0&
1(
1/
#47
0(
#48
1(
0/
#49
0(
#50
1(
1-
#51
0(
#52
1&
1(
#53
0(
#54
1(
0-
1/
#55
0(
#56
0&
1(
1-
#57
0(
#58
1&
1(
0-
0/
#59
0(
#60
0&
1(
1-
1/
#61
0(
#62
1&
1(
0/
#63
0(
#64
1(
0-
1/
#65
0(
#66
0&
1(
1-
#67
0(
#68
1&
1(
0-
0/
#69
0(
#70
0&
1(
1-
1/
#71
0(
#72
1&
1(
0-
0/
#73
0(
#74
0&
1(
1-
1/
#75
0(
#76
1&
1(
0-
0/
#77
0(
#78
0&
1(
1-
1/
#79
0(
#80
1&
1(
0/
#81
0(
#82
1(
1/
#83
0(
#84
1(
0-
#85
0(
#86
0&
1(
1-
#87
0(
#88
1&
1(
0/
#89
0(
#90
1(
0-
1/
#91
0(
#92
0&
1(
#93
0(
#94
1(
0/
#95
0(
#96
1(
1-
#97
0(
#98
1&
1(
0-
#99
0(
#100
0&
1(
1/
#101
0(
#102
1(
0/
#103
0(
#104
1(
1-
#105
0(
#106
1&
1(
0-
#107
0(
#108
0&
1(
1/
#109
0(
#110
1(
1-
0/
#111
0(
#112
1&
1(
0-
#113
0(
#114
0&
1(
1-
1/
#115
0(
#116
1&
1(
0-
0/
#117
0(
#118
0&
1(
1-
1/
#119
0(
#120
1&
1(
0/
#121
0(
#122
1(
1/
#123
0(
#124
1(
0-
#125
0(
#126
0&
1(
#127
0(
#128
1(
0/
#129
0(
#130
1(
#131
0(
#132
1(
1-
#133
0(
#134
1&
1(
0-
#135
0(
#136
0&
1(
1-
1/
#137
0(
#138
1&
1(
0-
0/
#139
0(
#140
0&
1(
1/
#141
0(
#142
1(
1-
0/
#143
0(
#144
1&
1(
#145
0(
#146
1(
0-
1/
#147
0(
#148
0&
1(
#149
0(
#150
1(
0/
#151
0(
#152
1(
#153
0(
#154
1(
#155
0(
#156
1(
1-
#157
0(
#158
1&
1(
0-
#159
0(
#160
0&
1(
1/
#161
0(
#162
1(
1-
0/
#163
0(
#164
1&
1(
0-
#165
0(
#166
0&
1(
1-
1/
#167
0(
#168
1&
1(
0-
0/
#169
0(
#170
0&
1(
1/
#171
0(
#172
1(
1-
0/
#173
0(
#174
1&
1(
0-
#175
0(
#176
0&
1(
1-
1/
#177
0(
#178
1&
1(
0/
#179
0(
#180
1(
1/
#181
0(
#182
1(
#183
0(
#184
1(
0-
#185
0(
#186
0&
1(
1-
#187
0(
#188
1&
1(
0/
#189
0(
#190
1(
1/
#191
0(
#192
1(
#193
0(
#194
1(
0-
#195
0(
#196
0&
1(
1-
#197
0(
#198
1&
1(
0-
0/
#199
0(
#200
0&
1(
1/
#201
0(
#202
1(
1-
0/
#203
0(
#204
1&
1(
#205
0(
#206
1(
1/
#207
0(
#208
1(
#209
0(
#210
1(
0-
#211
0(
#212
0&
1(
#213
0(
#214
1(
0/
#215
0(
#216
1(
#217
0(
#218
1(
1-
#219
0(
#220
1&
1(
0-
#221
0(
#222
0&
1(
1-
1/
#223
0(
#224
1&
1(
0-
0/
#225
0(
#226
0&
1(
1/
#227
0(
#228
1(
0/
#229
0(
#230
1(
#231
0(
#232
1(
#233
0(
#234
1(
1-
#235
0(
#236
1&
1(
0-
#237
0(
#238
0&
1(
1-
1/
#239
0(
#240
1&
1(
0-
0/
#241
0(
#242
0&
1(
1-
1/
#243
0(
#244
1&
1(
0-
0/
#245
0(
#246
0&
1(
1-
1/
#247
0(
#248
1&
1(
0-
0/
#249
0(
#250
0&
1(
1-
1/
#251
0(
#252
1&
1(
0-
0/
#253
0(
#254
0&
1(
1-
1/
#255
0(
#256
1&
1(
0-
0/
#257
0(
#258
0&
1(
1-
1/
#259
0(
#260
1&
1(
0-
0/
#261
0(
#262
0&
1(
1/
#263
0(
#264
1(
1-
0/
#265
0(
#266
1&
1(
#267
0(
#268
1(
0-
1/
#269
0(
#270
0&
1(
#271
0(
#272
1(
1-
0/
#273
0(
#274
1&
1(
0-
#275
0(
#276
0&
1(
1/
#277
0(
#278
1(
0/
#279
0(
#280
1(
1-
#281
0(
#282
1&
1(
0-
#283
0(
#284
0&
1(
1-
1/
#285
0(
#286
1&
1(
0/
#287
0(
#288
1(
0-
1/
#289
0(
#290
0&
1(
1-
#291
0(
#292
1&
1(
0-
0/
#293
0(
#294
0&
1(
1/
#295
0(
#296
1(
1-
0/
#297
0(
#298
1&
1(
0-
